cortexutils/__init__.py
cortexutils/analyzer.py
cortexutils/extractor.py
cortexutils/responder.py
cortexutils/worker.py
cortexutils-2.2.1.dist-info/licenses/LICENSE
cortexutils-2.2.1.dist-info/METADATA
cortexutils-2.2.1.dist-info/WHEEL
cortexutils-2.2.1.dist-info/top_level.txt
cortexutils-2.2.1.dist-info/RECORD
